{
  "kind": "radishflow.project-file",
  "schemaVersion": 1,
  "document": {
    "revision": 0,
    "flowsheet": {
      "name": "orphan-stream",
      "components": {
        "component-a": { "id": "component-a", "name": "Component A", "formula": null },
        "component-b": { "id": "component-b", "name": "Component B", "formula": null }
      },
      "streams": {
        "stream-feed": {
          "id": "stream-feed",
          "name": "Feed",
          "temperature_k": 300.0,
          "pressure_pa": 120000.0,
          "total_molar_flow_mol_s": 5.0,
          "overall_mole_fractions": {
            "component-a": 0.35,
            "component-b": 0.65
          },
          "phases": []
        },
        "stream-heated": {
          "id": "stream-heated",
          "name": "Heated Outlet",
          "temperature_k": 345.0,
          "pressure_pa": 95000.0,
          "total_molar_flow_mol_s": 0.0,
          "overall_mole_fractions": {
            "component-a": 0.5,
            "component-b": 0.5
          },
          "phases": []
        },
        "stream-liquid": {
          "id": "stream-liquid",
          "name": "Liquid Outlet",
          "temperature_k": 345.0,
          "pressure_pa": 95000.0,
          "total_molar_flow_mol_s": 0.0,
          "overall_mole_fractions": {
            "component-a": 0.5,
            "component-b": 0.5
          },
          "phases": []
        },
        "stream-vapor": {
          "id": "stream-vapor",
          "name": "Vapor Outlet",
          "temperature_k": 345.0,
          "pressure_pa": 95000.0,
          "total_molar_flow_mol_s": 0.0,
          "overall_mole_fractions": {
            "component-a": 0.5,
            "component-b": 0.5
          },
          "phases": []
        },
        "stream-orphan": {
          "id": "stream-orphan",
          "name": "Orphan Stream",
          "temperature_k": 320.0,
          "pressure_pa": 101325.0,
          "total_molar_flow_mol_s": 1.0,
          "overall_mole_fractions": {
            "component-a": 0.4,
            "component-b": 0.6
          },
          "phases": []
        }
      },
      "units": {
        "feed-1": {
          "id": "feed-1",
          "name": "Feed",
          "kind": "feed",
          "ports": [
            {
              "name": "outlet",
              "direction": "outlet",
              "kind": "material",
              "stream_id": "stream-feed"
            }
          ]
        },
        "heater-1": {
          "id": "heater-1",
          "name": "Heater",
          "kind": "heater",
          "ports": [
            {
              "name": "inlet",
              "direction": "inlet",
              "kind": "material",
              "stream_id": "stream-feed"
            },
            {
              "name": "outlet",
              "direction": "outlet",
              "kind": "material",
              "stream_id": "stream-heated"
            }
          ]
        },
        "flash-1": {
          "id": "flash-1",
          "name": "Flash Drum",
          "kind": "flash_drum",
          "ports": [
            {
              "name": "inlet",
              "direction": "inlet",
              "kind": "material",
              "stream_id": "stream-heated"
            },
            {
              "name": "liquid",
              "direction": "outlet",
              "kind": "material",
              "stream_id": "stream-liquid"
            },
            {
              "name": "vapor",
              "direction": "outlet",
              "kind": "material",
              "stream_id": "stream-vapor"
            }
          ]
        }
      }
    },
    "metadata": {
      "documentId": "example-orphan-stream",
      "title": "Orphan Stream Example",
      "schemaVersion": 1,
      "createdAt": "2026-04-11T00:00:00Z",
      "updatedAt": "2026-04-11T00:00:00Z"
    }
  }
}
